enumfields/__init__.py
enumfields/admin.py
enumfields/enums.py
enumfields/fields.py
enumfields/forms.py
enumfields/py.typed
enumfields/drf/__init__.py
enumfields/drf/fields.py
enumfields/drf/serializers.py
skip_django_choice_enumfields-2.0.0.dist-info/LICENSE
skip_django_choice_enumfields-2.0.0.dist-info/METADATA
skip_django_choice_enumfields-2.0.0.dist-info/WHEEL
skip_django_choice_enumfields-2.0.0.dist-info/top_level.txt
skip_django_choice_enumfields-2.0.0.dist-info/RECORD
