Metadata-Version: 2.1
Name: skip-django-choice-enumfields
Version: 2.0.0
Summary: Real Python Enums for Django.
Home-page: https://github.com/skip-pay/django-choice-enumfields
Author: HZDG, Lubos Matl
Author-email: matllubos@gmail.com
License: MIT
Classifier: Environment :: Web Environment
Classifier: Framework :: Django
Classifier: Framework :: Django :: 4.2
Classifier: Intended Audience :: Developers
Classifier: Operating System :: OS Independent
Classifier: Programming Language :: Python
Classifier: Programming Language :: Python :: 3.10
Classifier: Programming Language :: Python :: 3.11
Classifier: Topic :: Internet :: WWW/HTTP
License-File: LICENSE
